[
  {
    "constant": true,
    "inputs": [],
    "name": "owner",
    "outputs": [
      {
        "name": "",
        "type": "address"
      }
    ],
    "payable": false,
    "stateMutability": "view",
    "type": "function"
  },
  {
    "constant": true,
    "inputs": [],
    "name": "enigma",
    "outputs": [
      {
        "name": "",
        "type": "address"
      }
    ],
    "payable": false,
    "stateMutability": "view",
    "type": "function"
  },
  {
    "inputs": [],
    "payable": false,
    "stateMutability": "nonpayable",
    "type": "constructor"
  },
  {
    "constant": false,
    "inputs": [
      {
        "name": "_enigma",
        "type": "address"
      }
    ],
    "name": "setSecretContract",
    "outputs": [],
    "payable": false,
    "stateMutability": "nonpayable",
    "type": "function"
  },
  {
    "constant": false,
    "inputs": [
      {
        "name": "token_addr",
        "type": "address"
      },
      {
        "name": "from",
        "type": "address"
      },
      {
        "name": "token_id",
        "type": "uint256"
      }
    ],
    "name": "claim",
    "outputs": [],
    "payable": false,
    "stateMutability": "nonpayable",
    "type": "function"
  },
  {
    "constant": false,
    "inputs": [
      {
        "name": "token_addr",
        "type": "address"
      },
      {
        "name": "to",
        "type": "address"
      },
      {
        "name": "token_id",
        "type": "uint256"
      }
    ],
    "name": "release",
    "outputs": [],
    "payable": false,
    "stateMutability": "nonpayable",
    "type": "function"
  },
  {
    "constant": false,
    "inputs": [
      {
        "name": "_operator",
        "type": "address"
      },
      {
        "name": "_from",
        "type": "address"
      },
      {
        "name": "_tokenId",
        "type": "uint256"
      },
      {
        "name": "_data",
        "type": "bytes"
      }
    ],
    "name": "onERC721Received",
    "outputs": [
      {
        "name": "",
        "type": "bytes4"
      }
    ],
    "payable": false,
    "stateMutability": "nonpayable",
    "type": "function"
  }
]